ed318_pydantic/__init__.py
ed318_pydantic/geometries.py
ed318_pydantic/models.py
ed318_pydantic/types.py
ed318_pydantic/util.py
ed318_pydantic-0.2.1.dist-info/METADATA
ed318_pydantic-0.2.1.dist-info/WHEEL
ed318_pydantic-0.2.1.dist-info/RECORD
