Metadata-Version: 2.4
Name: ed318-pydantic
Version: 0.2.1
Summary: ED-318 Pydantic Models
Author-email: Lasse Fröhner <lasse@starcopter.com>
Requires-Python: >=3.13
Requires-Dist: geojson-pydantic>=1.2.0
Requires-Dist: pydantic>=2.10.6
